aplotme/__init__.py
aplotme/animate.py
aplotme-0.0.3.dist-info/METADATA
aplotme-0.0.3.dist-info/WHEEL
aplotme-0.0.3.dist-info/top_level.txt
aplotme-0.0.3.dist-info/RECORD
